nbnpy/__init__.py
nbnpy/nbn.py
nbnpy-0.5.0.dist-info/LICENSE
nbnpy-0.5.0.dist-info/WHEEL
nbnpy-0.5.0.dist-info/METADATA
nbnpy-0.5.0.dist-info/RECORD
