Metadata-Version: 2.1
Name: nbnpy
Version: 0.5.0
Summary: Unofficial NBN API wrapper
Home-page: https://github.com/diabolical-ninja/nbnpy
License: MIT
Author: Yass
Requires-Python: >=3.8,<4.0
Classifier: License :: OSI Approved :: MIT License
Classifier: Programming Language :: Python :: 3
Classifier: Programming Language :: Python :: 3.10
Classifier: Programming Language :: Python :: 3.8
Classifier: Programming Language :: Python :: 3.9
Requires-Dist: httpx (>=0.23.0,<0.24.0)
Project-URL: Documentation, https://nbnpy.readthedocs.io
Project-URL: Repository, https://github.com/diabolical-ninja/nbnpy
